uipath_langchain_client/__init__.py
uipath_langchain_client/__version__.py
uipath_langchain_client/base_client.py
uipath_langchain_client/factory.py
uipath_langchain_client/settings.py
uipath_langchain_client/clients/anthropic/__init__.py
uipath_langchain_client/clients/anthropic/chat_models.py
uipath_langchain_client/clients/azure/__init__.py
uipath_langchain_client/clients/azure/chat_models.py
uipath_langchain_client/clients/azure/embeddings.py
uipath_langchain_client/clients/bedrock/__init__.py
uipath_langchain_client/clients/bedrock/chat_models.py
uipath_langchain_client/clients/bedrock/embeddings.py
uipath_langchain_client/clients/bedrock/utils.py
uipath_langchain_client/clients/google/__init__.py
uipath_langchain_client/clients/google/chat_models.py
uipath_langchain_client/clients/google/embeddings.py
uipath_langchain_client/clients/normalized/__init__.py
uipath_langchain_client/clients/normalized/chat_models.py
uipath_langchain_client/clients/normalized/embeddings.py
uipath_langchain_client/clients/openai/__init__.py
uipath_langchain_client/clients/openai/chat_models.py
uipath_langchain_client/clients/openai/embeddings.py
uipath_langchain_client/clients/vertexai/__init__.py
uipath_langchain_client/clients/vertexai/chat_models.py
uipath_langchain_client-1.0.0.dist-info/METADATA
uipath_langchain_client-1.0.0.dist-info/WHEEL
uipath_langchain_client-1.0.0.dist-info/RECORD
