Metadata-Version: 2.4
Name: uipath-langchain-client
Version: 1.0.0
Summary: LangChain-compatible chat models and embeddings for UiPath's LLM services
Requires-Python: >=3.11
Requires-Dist: langchain>=1.2.7
Requires-Dist: uipath-llm-client>=1.0.0
Provides-Extra: all
Requires-Dist: langchain-anthropic>=1.3.1; extra == 'all'
Requires-Dist: langchain-aws>=1.2.1; extra == 'all'
Requires-Dist: langchain-azure-ai>=1.0.0; extra == 'all'
Requires-Dist: langchain-google-genai>=4.2.0; extra == 'all'
Requires-Dist: langchain-google-vertexai>=3.2.1; extra == 'all'
Requires-Dist: langchain-openai>=1.1.7; extra == 'all'
Provides-Extra: anthropic
Requires-Dist: langchain-anthropic>=1.3.1; extra == 'anthropic'
Provides-Extra: aws
Requires-Dist: langchain-aws>=1.2.1; extra == 'aws'
Provides-Extra: azure
Requires-Dist: langchain-azure-ai>=1.0.0; extra == 'azure'
Provides-Extra: google
Requires-Dist: langchain-google-genai>=4.2.0; extra == 'google'
Provides-Extra: openai
Requires-Dist: langchain-openai>=1.1.7; extra == 'openai'
Provides-Extra: vertexai
Requires-Dist: langchain-google-vertexai>=3.2.1; extra == 'vertexai'
